kds/__init__.py
kds/metrics.py
kds-0.1.3.dist-info/LICENSE.txt
kds-0.1.3.dist-info/METADATA
kds-0.1.3.dist-info/WHEEL
kds-0.1.3.dist-info/top_level.txt
kds-0.1.3.dist-info/RECORD
